queenbee_local/__init__.py
queenbee_local/cli.py
queenbee_local/helper.py
queenbee_local-0.7.0.dist-info/LICENSE
queenbee_local-0.7.0.dist-info/METADATA
queenbee_local-0.7.0.dist-info/WHEEL
queenbee_local-0.7.0.dist-info/entry_points.txt
queenbee_local-0.7.0.dist-info/top_level.txt
queenbee_local-0.7.0.dist-info/RECORD
