Metadata-Version: 2.1
Name: queenbee-local
Version: 0.7.0
Summary: Queenbee local provides a helper module for running queenbee recipes on desktop
Author: Ladybug Tools
Author-email: info@ladybug.tools
License: AGPL-3.0
Classifier: Programming Language :: Python :: 3.7
Classifier: Programming Language :: Python :: Implementation :: CPython
Classifier: License :: OSI Approved :: GNU Affero General Public License v3
Classifier: Operating System :: OS Independent
License-File: LICENSE
Requires-Dist: queenbee>=1.28.2
Requires-Dist: luigi==3.3.0
Requires-Dist: click>=7.1.2
Requires-Dist: click_plugins>=1.1.1
